LICENSE.txt
MANIFEST.in
README.md
setup.cfg
setup.py
face_cropper/__init__.py
face_cropper.egg-info/PKG-INFO
face_cropper.egg-info/SOURCES.txt
face_cropper.egg-info/dependency_links.txt
face_cropper.egg-info/requires.txt
face_cropper.egg-info/top_level.txt
face_cropper/cli/__init__.py
face_cropper/cli/input.py
face_cropper/cli/output.py
face_cropper/core/__init__.py
face_cropper/core/cropper.py
face_cropper/core/detector.py
face_cropper/core/selector.py
face_cropper/exceptions/__init__.py
face_cropper/exceptions/above_threshold_exception.py
face_cropper/exceptions/invalid_saving_path_exception.py
face_cropper/exceptions/no_face_exception.py
face_cropper/tests/__init__.py
face_cropper/tests/functional/__init__.py
face_cropper/tests/functional/test_crop_command.py
face_cropper/tests/functional/test_crop_function.py
face_cropper/tests/unit/__init__.py
face_cropper/tests/unit/test_detector.py
face_cropper/tests/unit/test_selector.py