Metadata-Version: 2.1
Name: face-cropper
Version: 1.0.0
Summary: A image cropping library
Home-page: https://github.com/Dave-Lopper/face_cropper
Author: Alexis Haim
Author-email: alexishaim@outlook.fr
License: UNKNOWN
Keywords: computer vision,crop,face recognition
Platform: UNKNOWN
Classifier: Programming Language :: Python :: 3
Classifier: License :: OSI Approved :: MIT License
Classifier: Operating System :: OS Independent
